selenium_wire_lw-3.0.2.dist-info/licenses/LICENSE
seleniumwire/__init__.py
seleniumwire/backend.py
seleniumwire/exceptions.py
seleniumwire/handler.py
seleniumwire/har.py
seleniumwire/inspect.py
seleniumwire/options.py
seleniumwire/py.typed
seleniumwire/request.py
seleniumwire/server.py
seleniumwire/storage.py
seleniumwire/utils.py
seleniumwire/webdriver.py
seleniumwire/helpers/cache.py
selenium_wire_lw-3.0.2.dist-info/METADATA
selenium_wire_lw-3.0.2.dist-info/WHEEL
selenium_wire_lw-3.0.2.dist-info/top_level.txt
selenium_wire_lw-3.0.2.dist-info/RECORD
