Metadata-Version: 2.4
Name: selenium-wire-lw
Version: 3.0.2
Summary: Extends Selenium to give you the ability to inspect requests made by the browser, with built-in support for undetected-geckodriver-lw
Author-email: LunarWatcher <oliviawolfie@pm.me>
License-Expression: MIT
Project-URL: Homepage, https://github.com/LunarWatcher/selenium-wire
Project-URL: Documentation, https://github.com/LunarWatcher/selenium-wire
Project-URL: Repository, https://github.com/LunarWatcher/selenium-wire.git
Project-URL: Issues, https://github.com/LunarWatcher/selenium-wire/issues
Project-URL: Changelog, https://github.com/LunarWatcher/selenium-wire/blob/master/CHANGELOG.md
Keywords: selenium,archival,archiving,selenium-wire
Classifier: Development Status :: 5 - Production/Stable
Classifier: Environment :: Console
Classifier: Intended Audience :: Developers
Classifier: Topic :: System :: Archiving
Classifier: Topic :: Utilities
Classifier: Programming Language :: Python :: 3
Classifier: Programming Language :: Python :: 3.12
Classifier: Programming Language :: Python :: 3.13
Classifier: Programming Language :: Python :: 3.14
Classifier: Operating System :: POSIX :: Linux
Classifier: Operating System :: MacOS
Classifier: Operating System :: Microsoft :: Windows
Requires-Python: >=3.12
License-File: LICENSE
Requires-Dist: selenium>=4.10.0
Requires-Dist: mitmproxy>=12.2.0
Requires-Dist: brotli>=1.1.0
Requires-Dist: zstd>=1.5.7.2
Provides-Extra: uf
Requires-Dist: undetected-geckodriver-lw; extra == "uf"
Dynamic: license-file
